spud/__init__.py
spud/context_processors.py
spud/defaults.py
spud/exceptions.py
spud/exif.py
spud/managers.py
spud/media.py
spud/models.py
spud/schema.txt
spud/serializers.py
spud/settings.py
spud/upload.py
spud/urls.py
spud/views.py
spud/wsgi.py
spud/management/__init__.py
spud/management/commands/__init__.py
spud/management/commands/process_actions.py
spud/migrations/0001_squashed_0015_auto_20170608_1709.py
spud/migrations/0002_auto_20180330_1742.py
spud/migrations/0003_auto_20180402_1041.py
spud/migrations/__init__.py
spud/templates/404.html
spud/templates/500.html
spud/templates/base.html
spud/templates/base_site.html
spud/templatetags/__init__.py
spud/templatetags/pipeline.py
spud/tests/__init__.py
spud/tests/conftest.py
spud/tests/settings.py
spud/tests/a_unit/__init__.py
spud/tests/a_unit/utils.py
spud/tests/a_unit/albums/__init__.py
spud/tests/a_unit/albums/test_models.py
spud/tests/a_unit/albums/test_search.py
spud/tests/a_unit/albums/test_serializer.py
spud/tests/a_unit/categorys/__init__.py
spud/tests/a_unit/categorys/test_models.py
spud/tests/a_unit/categorys/test_search.py
spud/tests/a_unit/categorys/test_serializer.py
spud/tests/a_unit/feedbacks/__init__.py
spud/tests/a_unit/feedbacks/test_models.py
spud/tests/a_unit/feedbacks/test_search.py
spud/tests/a_unit/feedbacks/test_serializer.py
spud/tests/a_unit/persons/__init__.py
spud/tests/a_unit/persons/test_models.py
spud/tests/a_unit/persons/test_search.py
spud/tests/a_unit/persons/test_serializer.py
spud/tests/a_unit/photos/__init__.py
spud/tests/a_unit/photos/test_models.py
spud/tests/a_unit/photos/test_search.py
spud/tests/a_unit/photos/test_serializer.py
spud/tests/a_unit/places/__init__.py
spud/tests/a_unit/places/test_models.py
spud/tests/a_unit/places/test_search.py
spud/tests/a_unit/places/test_serializer.py
spud/tests/b_integration/__init__.py
spud/tests/b_integration/conftest.py
spud/tests/b_integration/test_albums.py
spud/tests/b_integration/test_categorys.py
spud-2.1.1.dist-info/AUTHORS.txt
spud-2.1.1.dist-info/COPYING.txt
spud-2.1.1.dist-info/METADATA
spud-2.1.1.dist-info/WHEEL
spud-2.1.1.dist-info/top_level.txt
spud-2.1.1.dist-info/RECORD
